{
    "tenantId": "rjsh",
    "moduleName": "Chatbot",
    "CityLocaleMasterData": [
        {
            "cityName": "City A",
            "locale": "in_en",
            "tenantId": "rjsh.citya"
        },
        {
            "cityName": "शहर अ",
            "locale": "in_hi",
            "tenantId": "rjsh.citya"
        },
        {
            "cityName": "City B",
            "locale": "in_en",
            "tenantId": "rjsh.cityb"
        },
        {
            "cityName": "शहर ब",
            "locale": "in_hi",
            "tenantId": "rjsh.cityb"
        },
        {
            "cityName": "City C",
            "locale": "in_en",
            "tenantId": "rjsh.cityc"
        },
        {
            "cityName": "शहर स",
            "locale": "in_hi",
            "tenantId": "rjsh.cityc"
        },
        {
            "cityName": "City D",
            "locale": "in_en",
            "tenantId": "rjsh.cityd"
        },
        {
            "cityName": "शहर डी",
            "locale": "in_hi",
            "tenantId": "rjsh.cityd"
        },
        {
            "cityName": "City E",
            "locale": "in_en",
            "tenantId": "rjsh.citye"
        },
        {
            "cityName": "शहर ई",
            "locale": "in_hi",
            "tenantId": "rjsh.citye"
        }
    ]
}